RequestsProLibrary/DynamicTestCases.py
RequestsProLibrary/RequestsProKeywords.py
RequestsProLibrary/__init__.py
RequestsProLibrary/compat.py
RequestsProLibrary/version.py
robotframework_requestspro-1.2.9.dist-info/LICENSE
robotframework_requestspro-1.2.9.dist-info/METADATA
robotframework_requestspro-1.2.9.dist-info/WHEEL
robotframework_requestspro-1.2.9.dist-info/top_level.txt
robotframework_requestspro-1.2.9.dist-info/RECORD
