Metadata-Version: 2.1
Name: robotframework-requestspro
Version: 1.2.9
Summary: Robot Framework keyword library wrapper around requests
Home-page: https://github.com/sridharvpmca/robotframework-requestspro
Author: Sridhar VP
Author-email: sridharvpmca@gmail.com
License: MIT
Keywords: robotframework testing test automation http client requests
Platform: any
Classifier: Development Status :: 5 - Production/Stable
Classifier: License :: OSI Approved :: MIT License
Classifier: Operating System :: OS Independent
Classifier: Programming Language :: Python
Classifier: Topic :: Software Development :: Testing
License-File: LICENSE
Requires-Dist: pandas
Requires-Dist: requests
Requires-Dist: robotframework
Requires-Dist: robotframework-requests
Requires-Dist: urllib3
Requires-Dist: cqepyutils
